diffpy/__init__.py
diffpy/pdfgui/__init__.py
diffpy/pdfgui/tui.py
diffpy/pdfgui/utils.py
diffpy/pdfgui/version.py
diffpy/pdfgui/applications/__init__.py
diffpy/pdfgui/applications/pdfgui.py
diffpy/pdfgui/control/__init__.py
diffpy/pdfgui/control/calculation.py
diffpy/pdfgui/control/constraint.py
diffpy/pdfgui/control/controlerrors.py
diffpy/pdfgui/control/fitdataset.py
diffpy/pdfgui/control/fitstructure.py
diffpy/pdfgui/control/fitting.py
diffpy/pdfgui/control/organizer.py
diffpy/pdfgui/control/parameter.py
diffpy/pdfgui/control/pdfcomponent.py
diffpy/pdfgui/control/pdfdataset.py
diffpy/pdfgui/control/pdfguicontrol.py
diffpy/pdfgui/control/pdfguimacros.py
diffpy/pdfgui/control/pdflist.py
diffpy/pdfgui/control/pdfstructure.py
diffpy/pdfgui/control/plotter.py
diffpy/pdfgui/control/structureviewer.py
diffpy/pdfgui/gui/DesignNotes.txt
diffpy/pdfgui/gui/__init__.py
diffpy/pdfgui/gui/aboutdialog.py
diffpy/pdfgui/gui/adddatapanel.py
diffpy/pdfgui/gui/addphasepanel.py
diffpy/pdfgui/gui/blankpanel.py
diffpy/pdfgui/gui/bondangledialog.py
diffpy/pdfgui/gui/bondlengthdialog.py
diffpy/pdfgui/gui/calculationpanel.py
diffpy/pdfgui/gui/datasetconfigurepanel.py
diffpy/pdfgui/gui/datasetconstraintpanel.py
diffpy/pdfgui/gui/datasetpanel.py
diffpy/pdfgui/gui/datasetresultspanel.py
diffpy/pdfgui/gui/debugoptions.py
diffpy/pdfgui/gui/dopingseriespanel.py
diffpy/pdfgui/gui/errorreportdialog.py
diffpy/pdfgui/gui/errorreportdialog_control_fix.py
diffpy/pdfgui/gui/errorwrapper.py
diffpy/pdfgui/gui/extendedplotframe.py
diffpy/pdfgui/gui/fitnotebookpanel.py
diffpy/pdfgui/gui/fittree.py
diffpy/pdfgui/gui/gui_organization.txt
diffpy/pdfgui/gui/insertrowsdialog.py
diffpy/pdfgui/gui/journalpanel.py
diffpy/pdfgui/gui/main.py
diffpy/pdfgui/gui/mainframe.py
diffpy/pdfgui/gui/menuitems.txt
diffpy/pdfgui/gui/outputpanel.py
diffpy/pdfgui/gui/paneltest.py
diffpy/pdfgui/gui/parameterspanel.py
diffpy/pdfgui/gui/pdfguiglobals.py
diffpy/pdfgui/gui/pdfpanel.py
diffpy/pdfgui/gui/phaseconfigurepanel.py
diffpy.pdfgui-3.1.0.dist-info/AUTHORS.rst
diffpy.pdfgui-3.1.0.dist-info/LICENSE.rst
diffpy.pdfgui-3.1.0.dist-info/METADATA
diffpy.pdfgui-3.1.0.dist-info/WHEEL
diffpy.pdfgui-3.1.0.dist-info/entry_points.txt
diffpy.pdfgui-3.1.0.dist-info/top_level.txt
diffpy.pdfgui-3.1.0.dist-info/RECORD
