Metadata-Version: 2.2
Name: diffpy.pdfgui
Version: 3.1.0
Summary: GUI for PDF simulation and structure refinement.
Author-email: "Simon J.L. Billinge group" <simon.billinge@gmail.com>
Maintainer-email: "Simon J.L. Billinge group" <simon.billinge@gmail.com>
Project-URL: Homepage, https://github.com/diffpy/diffpy.pdfgui/
Project-URL: Issues, https://github.com/diffpy/diffpy.pdfgui/issues/
Keywords: PDF structure refinement GUI
Classifier: Development Status :: 5 - Production/Stable
Classifier: Environment :: Console
Classifier: Intended Audience :: Developers
Classifier: Intended Audience :: Science/Research
Classifier: License :: OSI Approved :: BSD License
Classifier: Operating System :: MacOS :: MacOS X
Classifier: Operating System :: Microsoft :: Windows
Classifier: Operating System :: POSIX
Classifier: Operating System :: Unix
Classifier: Programming Language :: Python :: 3.11
Classifier: Programming Language :: Python :: 3.12
Classifier: Programming Language :: Python :: 3.13
Classifier: Topic :: Scientific/Engineering :: Physics
Classifier: Topic :: Scientific/Engineering :: Chemistry
Requires-Python: <3.14,>=3.11
License-File: LICENSE.rst
License-File: AUTHORS.rst
Requires-Dist: numpy
Requires-Dist: wxpython
Requires-Dist: diffpy.pdffit2
Requires-Dist: diffpy.structure
Requires-Dist: diffpy.utils
Requires-Dist: matplotlib
